inputtr/__init__.py
inputtr/inputter.py
inputtr-0.0.5.dist-info/LICENSE
inputtr-0.0.5.dist-info/METADATA
inputtr-0.0.5.dist-info/WHEEL
inputtr-0.0.5.dist-info/top_level.txt
inputtr-0.0.5.dist-info/RECORD
