Metadata-Version: 2.1
Name: inputtr
Version: 0.0.5
Summary: Small library to get, validate and transform user input
Home-page: https://github.com/Hardi23/Inputter
Author: Joshua Oppel
Author-email: harddeving@gmail.com
License: UNKNOWN
Platform: UNKNOWN
Classifier: Intended Audience :: Developers
Classifier: License :: OSI Approved :: GNU General Public License v3 (GPLv3)
Classifier: Natural Language :: English
Classifier: Programming Language :: Python :: 3
Classifier: Programming Language :: Python :: 3.6
Classifier: Programming Language :: Python :: 3.7
Classifier: Programming Language :: Python :: 3.8
Requires-Python: >=3.6
License-File: LICENSE
